jeong_cal/__init__.py
jeong_cal/cal.py
jeong_cal-1.0.4.dist-info/METADATA
jeong_cal-1.0.4.dist-info/WHEEL
jeong_cal-1.0.4.dist-info/entry_points.txt
jeong_cal-1.0.4.dist-info/top_level.txt
jeong_cal-1.0.4.dist-info/RECORD
