Metadata-Version: 2.1
Name: jeong_cal
Version: 1.0.4
Summary: Default template for PDM package
Author-email: Jeonghoon2 <ukidd12@naver.com>
License: MIT
Project-URL: Homepage, https://github.com/Jeonghoon2/cal
Project-URL: Issues, https://github.com/Jeonghoon2/cal/issues
Requires-Python: >=3.9
Requires-Dist: haram-sum >=0.1.6
Requires-Dist: haram-sub >=0.1.3
Requires-Dist: jeong-mul >=0.1.3
